mcpserver/__init__.py
mcpserver/__main__.py
mcpserver/server.py
mcp_bookmark_server-0.1.4.dist-info/METADATA
mcp_bookmark_server-0.1.4.dist-info/WHEEL
mcp_bookmark_server-0.1.4.dist-info/entry_points.txt
mcp_bookmark_server-0.1.4.dist-info/top_level.txt
mcp_bookmark_server-0.1.4.dist-info/RECORD
