Metadata-Version: 2.4
Name: mcp-bookmark-server
Version: 0.1.4
Summary: MCP server to save and search bookmarks using OpenAI RAG
Author-email: Preeti Dewani <preetidewani1990@gmail.com>
License: MIT
Project-URL: Homepage, https://github.com/pree-dew/mcp-bookmark
Project-URL: Repository, https://github.com/pree-dew/mcp-bookmark
Project-URL: Bug Tracker, https://github.com/pree-dew/mcp-bookmark/issues
Keywords: mcp,bookmark,openai,rag,search,server
Classifier: Development Status :: 3 - Alpha
Classifier: Intended Audience :: Developers
Classifier: License :: OSI Approved :: MIT License
Classifier: Programming Language :: Python :: 3
Classifier: Programming Language :: Python :: 3.11
Classifier: Topic :: Software Development :: Libraries :: Python Modules
Classifier: Topic :: Internet :: WWW/HTTP :: Indexing/Search
Requires-Python: >=3.11
Requires-Dist: mcp[cli]>=1.13.1
Requires-Dist: openai>=1.106.1
